{"v":1,"lamport":1,"ops":[{"kind":"create_task","nonce":"3ab6863f242652eb34800cf9b445ec90","title":"getaway v2: create and validate data registries (cli/getaway/data/)","description":"Extract programs.json (26+british+iberia), banks.json, transfer_partners.json, seat_quality.json (~100 rows), regions.json (~40 codes), factors.json (12-factor judgment registry) from repo prose; research status_earning.json + points_pricing.json from program docs with sourced notes. Read only via registry.py / `getaway registry ...`.","type":"task","priority":2,"branch":"","parent":"","labels":null},{"kind":"add_criterion","id":"4aa707fba0f12d85e4752229a446ca49","text":"jq empty passes on all 8 files in cli/getaway/data/","script":""},{"kind":"add_criterion","id":"7b43cf27a9eb75de39e4d058bec336d7","text":"row counts reconcile against source tables (28 programs, 4 banks, ~100 seat-quality rows, ~40 regions, 12 factors)","script":""},{"kind":"add_criterion","id":"2c0d2afba3f325909278df0e5ab8784f","text":"every status_earning/points_pricing row carries a sourced note; uncertain rows say so","script":""}]}